setup.py
stateful/__init__.py
stateful/core/__init__.py
stateful/core/object.py
stateful/core/property.py
stateful/core/state.py
stateful/util/__init__.py
stateful/util/environ.py
stateful/util/timer.py
tests/__init__.py
tests/integration/__init__.py
tests/integration/test_object_property.py
tests/integration/test_timer_object.py
tests/integration/test_timer_object_property.py
tests/integration/test_timer_property.py
tests/unit/__init__.py
tests/unit/test_object.py
tests/unit/test_property.py
tests/unit/test_timer.py
tests/unit/util.py
stat3ful-3.0.0.dist-info/LICENSE.md
stat3ful-3.0.0.dist-info/METADATA
stat3ful-3.0.0.dist-info/WHEEL
stat3ful-3.0.0.dist-info/top_level.txt
stat3ful-3.0.0.dist-info/RECORD
