Metadata-Version: 2.1
Name: stat3ful
Version: 3.0.0
Summary: Property-like classes with expiration/change monitoring
Home-page: 
Author: aachn3
Author-email: n45t31@protonmail.com
Classifier: Programming Language :: Python :: 3
Classifier: Operating System :: OS Independent
Requires-Python: >=3.6.5
License-File: LICENSE.md
